blended_dataset_loop-0.1.0.dist-info/METADATA
blended_dataset_loop-0.1.0.dist-info/WHEEL
blended_dataset_loop-0.1.0.dist-info/license_files/LICENSE
blended_dataset_loop/__init__.py
blended_dataset_loop/blended_dataset_loop/__init__.py
blended_dataset_loop/blended_dataset_loop/ffi.py
blended_dataset_loop/blended_dataset_loop/blended_dataset_loop.so
blended_dataset_loop-0.1.0.dist-info/RECORD
