Metadata-Version: 2.3
Name: blended_dataset_loop
Version: 0.1.0
Classifier: Programming Language :: Rust
Classifier: Programming Language :: Python :: Implementation :: CPython
Classifier: Programming Language :: Python :: Implementation :: PyPy
Requires-Dist: numpy
Requires-Dist: cffi
Requires-Dist: pytest ; extra == 'dev'
Requires-Dist: black ~=24.0 ; extra == 'dev'
Requires-Dist: mypy ; extra == 'dev'
Provides-Extra: dev
License-File: LICENSE
Requires-Python: >=3.8
